bits/__init__.py
bits/retreat/__init__.py
bits/retreat/firestore.py
bits/retreat/hopin.py
bits/retreat/pathable.py
bits/retreat/registrant.py
bits/retreat/sendgrid.py
bits/retreat/slack.py
bits/retreat/swoogo.py
bits_retreat-0.0.23.dist-info/METADATA
bits_retreat-0.0.23.dist-info/WHEEL
bits_retreat-0.0.23.dist-info/top_level.txt
bits_retreat-0.0.23.dist-info/RECORD
