Metadata-Version: 2.1
Name: bits-retreat
Version: 0.0.23
Summary: BITS Retreat
Author: Lukas Karlsson
Author-email: karlsson@broadinstitute.org
License: Apache Software License
Requires-Dist: google-cloud-secret-manager
Requires-Dist: pyyaml
Requires-Dist: requests
